oven/__init__.py
oven/pointer/__init__.py
oven/pointer/pointer.py
oven/stdio/__init__.py
oven/stdio/io_stream.py
oven/stdio/stdio.py
oven/structs/__init__.py
oven/structs/binarytree.py
oven/structs/queue.py
oven/structs/stack.py
oven/structs/tree.py
oven-0.1.0.dist-info/LICENSE
oven-0.1.0.dist-info/METADATA
oven-0.1.0.dist-info/WHEEL
oven-0.1.0.dist-info/top_level.txt
oven-0.1.0.dist-info/RECORD
