Metadata-Version: 2.1
Name: oven
Version: 0.1.0
Summary: An util package that includes features from other languages' stdlib.
Home-page: https://github.com/davidmaamoaix/Oven
Author: David Ma
Author-email: davidma@davidma.cn
License: MIT
Platform: UNKNOWN
